WatsonxConnector/__init__.py
WatsonxConnector/connector.py
WatsonxConnector-0.0.8.dist-info/LICENSE
WatsonxConnector-0.0.8.dist-info/METADATA
WatsonxConnector-0.0.8.dist-info/WHEEL
WatsonxConnector-0.0.8.dist-info/top_level.txt
WatsonxConnector-0.0.8.dist-info/RECORD
