Metadata-Version: 2.1
Name: WatsonxConnector
Version: 0.0.8
Summary: IBM Watsonx API wrapper package for calling text generation and embedding requests
Home-page: https://github.com/jackpots28/watsonx_connector
Author: Jack Sims
Author-email: jack.m.sims@protonmail.com
License: Apache-2.0
Classifier: Development Status :: 4 - Beta
Classifier: Intended Audience :: Developers
Classifier: Intended Audience :: Information Technology
Classifier: License :: OSI Approved :: Apache Software License
Classifier: Operating System :: POSIX :: Linux
Classifier: Topic :: Utilities
Classifier: Programming Language :: Python :: 3.10
Classifier: Programming Language :: Python :: 3.11
Classifier: Programming Language :: Python :: 3.12
License-File: LICENSE
Requires-Dist: setuptools
Requires-Dist: wheel
Requires-Dist: requests
Requires-Dist: urllib3~=2.2.3
